LICENSE.md
MANIFEST.in
README.md
setup.py
pijaz/__init__.py
pijaz/product.py
pijaz/server_manager.py
pijaz_sdk.egg-info/PKG-INFO
pijaz_sdk.egg-info/SOURCES.txt
pijaz_sdk.egg-info/dependency_links.txt
pijaz_sdk.egg-info/not-zip-safe
pijaz_sdk.egg-info/requires.txt
pijaz_sdk.egg-info/top_level.txt