Metadata-Version: 1.0
Name: pijaz-sdk
Version: 0.1
Summary: Pijaz Platform Software Development Kit
Home-page: UNKNOWN
Author: Chad Phillips
Author-email: chad@pijaz.com
License: UNKNOWN
Keywords: pijaz graphics sdk synthesizer platform
Platform: UNKNOWN
Classifier: Programming Language :: Python
Classifier: Intended Audience :: Developers
Classifier: License :: OSI Approved :: MIT License
Classifier: Topic :: Artistic Software
Classifier: Topic :: Multimedia :: Graphics
Classifier: Topic :: Multimedia :: Graphics :: Editors
Classifier: Topic :: Software Development :: Libraries :: Application Frameworks
Classifier: Topic :: Software Development :: Libraries :: Python Modules
